{
    "sourceFile": "README.md",
    "activeCommit": 0,
    "commits": [
        {
            "activePatchIndex": 6,
            "patches": [
                {
                    "date": 1760856939646,
                    "content": "Index: \n===================================================================\n--- \n+++ \n"
                },
                {
                    "date": 1760856948639,
                    "content": "Index: \n===================================================================\n--- \n+++ \n@@ -1,1 +1,1 @@\n-    \n\\ No newline at end of file\n+# a\n\\ No newline at end of file\n"
                },
                {
                    "date": 1760856957427,
                    "content": "Index: \n===================================================================\n--- \n+++ \n@@ -1,1 +1,1 @@\n-# a\n\\ No newline at end of file\n+# total\n\\ No newline at end of file\n"
                },
                {
                    "date": 1760856964252,
                    "content": "Index: \n===================================================================\n--- \n+++ \n@@ -1,1 +1,2 @@\n-# total\n\\ No newline at end of file\n+# Total Items\r\n+\r\n"
                },
                {
                    "date": 1760856972750,
                    "content": "Index: \n===================================================================\n--- \n+++ \n@@ -1,2 +1,3 @@\n # Total Items\r\n \r\n+インベントリ内でアイテムにマウスをホバーした時に、ツールチップに合計数量を表示するModです。\n\\ No newline at end of file\n"
                },
                {
                    "date": 1760856996598,
                    "content": "Index: \n===================================================================\n--- \n+++ \n@@ -1,3 +1,3 @@\n # Total Items\r\n \r\n-インベントリ内でアイテムにマウスをホバーした時に、ツールチップに合計数量を表示するModです。\n\\ No newline at end of file\n+インベントリ内でアイテムにマウスをホバーした時に、ツールチップにそのアイテムの合計数量を表示するModです。\n\\ No newline at end of file\n"
                },
                {
                    "date": 1760857006894,
                    "content": "Index: \n===================================================================\n--- \n+++ \n@@ -1,3 +1,3 @@\n # Total Items\r\n \r\n-インベントリ内でアイテムにマウスをホバーした時に、ツールチップにそのアイテムの合計数量を表示するModです。\n\\ No newline at end of file\n+インベントリ内でアイテムにマウスをホバーした時に、ツールチップにインベントリ内にあるそのアイテムの合計数量を表示するModです。\n\\ No newline at end of file\n"
                }
            ],
            "date": 1760856939646,
            "name": "Commit-0",
            "content": "    "
        }
    ]
}